LICENSE
MANIFEST.in
README.rst
mondrian_composition.png
setup.cfg
setup.py
mpdl/__init__.py
mpdl/colours.py
mpdl/defaults.py
mpdl/interpreter.py
mpdl/mpdl.py
mpdl/mpdl_console.py
mpdl/mpdl_exception.py
mpdl/mpdl_instruction.py
mpdl/painter.py
mpdl/parser.py
mpdl/ppm_writer.py
mpdl/rectangles.py
mpdl.egg-info/PKG-INFO
mpdl.egg-info/SOURCES.txt
mpdl.egg-info/dependency_links.txt
mpdl.egg-info/entry_points.txt
mpdl.egg-info/requires.txt
mpdl.egg-info/top_level.txt
tests/__init__.py
tests/test_interpreter.py
tests/test_mpdl.py
tests/test_painter.py
tests/test_parser.py
tests/test_ppm_writer.py