Metadata-Version: 1.1
Name: mpdl
Version: 1.0.0
Summary: Mondrian Painting Description Language interpreter
Home-page: https://github.com/LeopoldTal/mpdl-py
Author: Leopold de Gaillande
Author-email: leopold.tal.dg@gmail.com
License: MIT
Keywords: mpdl interpreter esoteric esolang
Platform: UNKNOWN
Classifier: Development Status :: 3 - Alpha
Classifier: Intended Audience :: Developers
Classifier: License :: OSI Approved :: MIT License
Classifier: Natural Language :: English
Classifier: Programming Language :: Python :: 3
Classifier: Topic :: Software Development :: Interpreters
